LICENSE
MANIFEST.in
README.md
setup.py
apimaticcalculatorpython1/__init__.py
apimaticcalculatorpython1/api_helper.py
apimaticcalculatorpython1/apimaticcalculatorpython1_client.py
apimaticcalculatorpython1/configuration.py
apimaticcalculatorpython1/decorators.py
apimaticcalculatorpython1.egg-info/PKG-INFO
apimaticcalculatorpython1.egg-info/SOURCES.txt
apimaticcalculatorpython1.egg-info/dependency_links.txt
apimaticcalculatorpython1.egg-info/requires.txt
apimaticcalculatorpython1.egg-info/top_level.txt
apimaticcalculatorpython1/controllers/__init__.py
apimaticcalculatorpython1/controllers/base_controller.py
apimaticcalculatorpython1/controllers/simple_calculator.py
apimaticcalculatorpython1/exceptions/__init__.py
apimaticcalculatorpython1/exceptions/api_exception.py
apimaticcalculatorpython1/http/__init__.py
apimaticcalculatorpython1/http/http_call_back.py
apimaticcalculatorpython1/http/http_client.py
apimaticcalculatorpython1/http/http_context.py
apimaticcalculatorpython1/http/http_method_enum.py
apimaticcalculatorpython1/http/http_request.py
apimaticcalculatorpython1/http/http_response.py
apimaticcalculatorpython1/http/requests_client.py
apimaticcalculatorpython1/http/auth/__init__.py
apimaticcalculatorpython1/http/auth/basic_auth.py
apimaticcalculatorpython1/models/__init__.py
apimaticcalculatorpython1/models/operation_type.py
tests/__init__.py
tests/http_response_catcher.py
tests/test_helper.py
tests/controllers/__init__.py
tests/controllers/controller_test_base.py
tests/controllers/test_simple_calculator.py